{
  "street_1": {
    "type": "string",
    "example": "Baker Street"
  },
  "street_2": {
    "type": [
      "string",
      "null"
    ],
    "example": "Marylebone"
  },
  "street_number": {
    "type": [
      "integer",
      "null"
    ],
    "example": 221
  },
  "street_number_suffix": {
    "type": [
      "string",
      "null"
    ],
    "example": "B"
  },
  "postal_code": {
    "type": [
      "string",
      "null"
    ],
    "example": "NW1 6XE"
  },
  "city": {
    "type": "string",
    "example": "London"
  },
  "state_code": {
    "type": [
      "string",
      "null"
    ],
    "pattern": "^[A-Z\\d]{1,3}$",
    "example": "ENG",
    "description": "The country subdivision code (second part of the ISO 3166-2 format). Required by some carriers for the United States or Canada."
  },
  "country_code": {
    "$ref": "../includes/country-code.json"
  },
  "first_name": {
    "type": "string",
    "example": "Sherlock"
  },
  "last_name": {
    "type": "string",
    "example": "Holmes"
  },
  "company": {
    "type": [
      "string",
      "null"
    ],
    "example": "Holmes Investigations"
  },
  "email": {
    "type": [
      "string",
      "null"
    ],
    "example": "s.holmes@holmesinvestigations.com"
  },
  "phone_number": {
    "type": [
      "string",
      "null"
    ],
    "example": "+31 234 567 890"
  }
}
